[
  {
    "id": 11,
    "name": "Quadro olio su tela firmato Antonio Ponticelli",
    "section": "antiquariato",
    "category": "arte",
    "location": "24052, Azzano San Paolo",
    "condition": "Buone",
    "postedAt": "2026-02-09",
    "description": "Vendo dipinto originale a olio su tela firmato Antonio Ponticelli, pittore napoletano.\nSoggetto paesaggio rurale con abitazione e strada.\n\nMisure tela circa 50x40 cm, con cornice 60x50 cm.\nCornice originale d'epoca.\nSul retro e' presente documentazione di galleria con quotazioni storiche.\n\nStato conservativo buono, cornice con normale usura.\nOggetto autentico, non stampa.\n\nPossibile spedizione o ritiro diretto.\nPrezzo trattabile con buon senso.",
    "price": 99,
    "year": "",
    "dimensions": "63x43cm",
    "status": "available",
    "featured": true,
    "image": "assets/products/1_1.jpg",
    "gallery": [
      "assets/products/1_1.jpg",
      "assets/products/1_2.jpg",
      "assets/products/2_1.jpg",
      "assets/products/2_2.jpg",
      "assets/products/3_1.jpg",
      "assets/products/3_2.jpg",
      "assets/products/4_1.jpg",
      "assets/products/4_2.jpg",
      "assets/products/5_1.jpg",
      "assets/products/5_2.jpg"
    ],
    "stripeLinkBuy": "",
    "paypalBuy": "",
    "whatsappText": ""
  }
]
